{
  "_class": "shapeGroup",
  "clippingMaskMode": 0,
  "do_objectID": "4346F71F-D9B1-438E-B380-AE0CB8B4105B",
  "exportOptions": {
    "_class": "exportOptions",
    "do_objectID": "C680B616-4939-4B77-BDD7-B7B38DEDCDAD",
    "exportFormats": [
    ],
    "includedLayerIds": [
    ],
    "layerOptions": 0,
    "shouldTrim": false
  },
  "frame": {
    "_class": "rect",
    "constrainProportions": false,
    "do_objectID": "992458C4-EC30-49F9-986E-B003B5114813",
    "height": 62,
    "width": 531,
    "x": 21,
    "y": 0
  },
  "hasClickThrough": false,
  "hasClippingMask": false,
  "isFlippedHorizontal": false,
  "isFlippedVertical": false,
  "isLocked": false,
  "isVisible": true,
  "layerListExpandedType": 1,
  "layers": [
    {
      "class": "shapePath",
      "id": "6AF0C9C9-5568-4595-9E3F-8091B3D980BB"
    }
  ],
  "name": "Shape",
  "nameIsFixed": false,
  "resizingConstraint": 63,
  "resizingType": 0,
  "rotation": 0,
  "shouldBreakMaskChain": false,
  "style": {
    "_class": "style",
    "contextSettings": {
      "_class": "graphicsContextSettings",
      "blendMode": 0,
      "do_objectID": "0FA6E901-4BB7-47C3-AFBA-31414E1DF48F",
      "opacity": 0.1
    },
    "do_objectID": "22887804-0FE5-4BF9-8CB8-EDF744356D8D",
    "endDecorationType": 0,
    "fills": [
      {
        "_class": "fill",
        "color": {
          "_class": "color",
          "alpha": 1,
          "blue": 0.9411764705882353,
          "green": 0.3764705882352941,
          "red": 0.580392156862745
        },
        "fillType": 0,
        "isEnabled": true,
        "noiseIndex": 0,
        "noiseIntensity": 0,
        "patternFillType": 1,
        "patternTileScale": 1
      }
    ],
    "miterLimit": 10,
    "startDecorationType": 0
  },
  "windingRule": 0
}