{
  "_class": "group",
  "booleanOperation": -1,
  "clippingMaskMode": 0,
  "do_objectID": "64012EB0-7B3D-47DC-BBA5-6E732E087C78",
  "exportOptions": {
    "_class": "exportOptions",
    "do_objectID": "ED450B40-0F3F-4899-A354-E6031F57C215",
    "exportFormats": [
    ],
    "includedLayerIds": [
    ],
    "layerOptions": 0,
    "shouldTrim": false
  },
  "frame": {
    "_class": "rect",
    "constrainProportions": false,
    "do_objectID": "13511401-B91F-45F5-B459-D752D3FCB95B",
    "height": 235,
    "width": 245,
    "x": 192,
    "y": 190
  },
  "hasClickThrough": false,
  "hasClippingMask": false,
  "isFixedToViewport": false,
  "isFlippedHorizontal": true,
  "isFlippedVertical": false,
  "isLocked": false,
  "isVisible": true,
  "layerListExpandedType": 2,
  "layers": [
    {
      "class": "rectangle",
      "id": "6F78DD75-30CB-4A10-A05F-E0C443FA3BD6"
    },
    {
      "class": "rectangle",
      "id": "39E74805-2C08-4F06-BADE-B79498EF359F"
    },
    {
      "class": "rectangle",
      "id": "8DC1D373-66B1-417B-8F96-C918E1592465"
    }
  ],
  "name": "Group",
  "nameIsFixed": false,
  "resizingConstraint": 63,
  "resizingType": 0,
  "rotation": 0,
  "shouldBreakMaskChain": false,
  "style": {
    "_class": "style",
    "do_objectID": "3FA66AF7-D4B2-4B1C-B1EB-5A5C60FBBE02",
    "endMarkerType": 0,
    "miterLimit": 10,
    "startMarkerType": 0,
    "windingRule": 1
  }
}